qifeaturex/__init__.py
qifeaturex/bipartite.py
qifeaturex/feature_extractor.py
qifeaturex/states.py
qifeaturex/features/__init__.py
qifeaturex/features/bell.py
qifeaturex/features/coherence.py
qifeaturex/features/distance.py
qifeaturex/features/entanglement.py
qifeaturex/features/entropy.py
qifeaturex/ml/__init__.py
qifeaturex/ml/transformer.py
qifeaturex-0.1.1.dist-info/licenses/LICENSE
qifeaturex-0.1.1.dist-info/METADATA
qifeaturex-0.1.1.dist-info/WHEEL
qifeaturex-0.1.1.dist-info/top_level.txt
qifeaturex-0.1.1.dist-info/RECORD
